source/system_control/system_components/uart/uart_transreceiver/uart_tx/uart_tx.vhd
library ieee;
    use ieee.std_logic_1164.all;
    use ieee.numeric_std.all;

library work;
    use work.uart_tx_pkg.all;


entity uart_tx is
    port (
        uart_tx_clocks   : in uart_tx_clock_group;
        uart_tx_FPGA_out : out uart_tx_FPGA_output_group;
        uart_tx_data_in  : in uart_tx_data_input_group;
        uart_tx_data_out : out uart_tx_data_output_group
    );
end entity;

architecture rtl of uart_tx is

    alias clock is uart_tx_clocks.clock;

    --------------------------------------------------
    procedure shift_and_register
    (
        signal shift_register : inout std_logic_vector
    ) is
    begin
        shift_register <= shift_register(shift_register'left-1 downto 0) & '1';
    end shift_and_register; 

    --------------------------------------------------
    procedure shift_and_register_when
    (
        shift_is_requested : boolean;
        signal shift_register : inout std_logic_vector 
    ) is
    begin
        if shift_is_requested then
            shift_and_register(shift_register);
        end if;
        
    end shift_and_register_when;

    --------------------------------------------------
    procedure load_data_with_start_and_stop_bits_to
    (
        signal transmit_register : out std_logic_vector;
        data_to_be_transmitted : in std_logic_vector
    ) is
    begin

        transmit_register <= '0' & data_to_be_transmitted & '0';

    end load_data_with_start_and_stop_bits_to;

    signal transmit_register : std_logic_vector(9 downto 0) := (others => '0');
    signal transmit_bit_counter : natural range 0 to 15;
    constant clock_in_uart_bit : natural := 6;
    constant bit_counter_high : natural := clock_in_uart_bit - 1;
    signal transmit_data_bit_counter : natural range 0 to 15;


begin

    uart_tx_FPGA_out <= (uart_tx => transmit_register(transmit_register'left));

------------------------------------------------------------------------
    uart_transmitter : process(clock)

        type t_uart_tansmitter is (idle, transmit);
        variable st_uart_tansmitter : t_uart_tansmitter := idle;

    begin
        if rising_edge(clock) then

            CASE st_uart_tansmitter is
                WHEN idle =>
                    st_uart_tansmitter := idle;
                    transmit_data_bit_counter <= 0;
                    transmit_bit_counter <= bit_counter_high;
                    if uart_tx_data_in.uart_transmit_is_requested then
                        load_data_with_start_and_stop_bits_to(transmit_register, uart_tx_data_in.data_to_be_transmitted);
                        st_uart_tansmitter := transmit; 
                    end if;
                WHEN transmit =>
                    if transmit_bit_counter = 0 then
                        transmit_bit_counter <= bit_counter_high;
                        shift_and_register(transmit_register); 
                        transmit_data_bit_counter <= transmit_data_bit_counter + 1;
                        if transmit_data_bit_counter = 9 then
                            st_uart_tansmitter := idle;
                        end if;
                    else
                        transmit_bit_counter <= transmit_bit_counter - 1;
                    end if;

            end CASE;

        end if; --rising_edge
    end process uart_transmitter;	

------------------------------------------------------------------------
end rtl;

source/system_control/system_components/uart/uart_transreceiver/uart_tx/simulation/tb_uart_tx.vhd
LIBRARY ieee  ; 
LIBRARY std  ; 
    USE ieee.NUMERIC_STD.all  ; 
    USE ieee.std_logic_1164.all  ; 
    USE ieee.std_logic_textio.all  ; 
    use ieee.math_real.all;
    USE std.textio.all  ; 

library work;
    use work.uart_tx_pkg.all;

entity tb_uart_tx is
end;

architecture sim of tb_uart_tx is
    signal rstn : std_logic;

    signal simulation_running : boolean;
    signal simulator_clock : std_logic;
    signal clocked_reset : std_logic;
    constant clock_per : time := 1 ns;
    constant clock_half_per : time := 0.5 ns;
    constant simtime_in_clocks : integer := 150;

    signal uart_tx_clocks   : uart_tx_clock_group;
    signal uart_tx_FPGA_out : uart_tx_FPGA_output_group;
    signal uart_tx_data_in  : uart_tx_data_input_group;
    signal uart_tx_data_out : uart_tx_data_output_group;

    signal simulation_counter : natural := 0;

begin

------------------------------------------------------------------------
    simtime : process
    begin
        simulation_running <= true;
        wait for simtime_in_clocks*clock_per;
        simulation_running <= false;
        wait;
    end process simtime;	

------------------------------------------------------------------------
    sim_clock_gen : process
    begin
        simulator_clock <= '0';
        rstn <= '0';
        simulator_clock <= '0';
        wait for clock_half_per;
        while simulation_running loop
            wait for clock_half_per;
                rstn <= '1';
                simulator_clock <= not simulator_clock;
            end loop;
        wait;
    end process;
------------------------------------------------------------------------

    clocked_reset_generator : process(simulator_clock, rstn)
    begin
        if rstn = '0' then
        -- reset state
            clocked_reset <= '0';
    
        elsif rising_edge(simulator_clock) then
            clocked_reset <= '1';
            simulation_counter <= simulation_counter + 1;
            init_uart(uart_tx_data_in);

            CASE simulation_counter is
                WHEN 5 =>
                    transmit_8bit_data_package(uart_tx_data_in, x"AC");
                WHEN others => -- do nothing
            end CASE;
    
        end if; -- rstn
    end process clocked_reset_generator;	
------------------------------------------------------------------------

    uart_tx_clocks <= (clock => simulator_clock);

    u_uart_tx : uart_tx
    port map( uart_tx_clocks,
    	  uart_tx_FPGA_out,
    	  uart_tx_data_in,
    	  uart_tx_data_out);
end sim;

source/system_control/system_components/uart/uart_transreceiver/uart_tx/simulation/tb_uart_tx.vcd
$date
  Sun Jun 06 22:43:52 2021
$end
$version
  GHDL v0
$end
$timescale
  1 fs
$end
$scope module standard $end
$upscope $end
$scope module std_logic_1164 $end
$upscope $end
$scope module numeric_std $end
$upscope $end
$scope module textio $end
$upscope $end
$scope module std_logic_textio $end
$upscope $end
$scope module math_real $end
$upscope $end
$scope module uart_tx_pkg $end
$upscope $end
$scope module tb_uart_tx $end
$var reg 1 ! rstn $end
$var reg 1 " simulation_running $end
$var reg 1 # simulator_clock $end
$var reg 1 $ clocked_reset $end
$comment uart_tx_clocks is not handled $end
$comment uart_tx_fpga_out is not handled $end
$comment uart_tx_data_in is not handled $end
$comment uart_tx_data_out is not handled $end
$var integer 32 % simulation_counter $end
$scope module u_uart_tx $end
$comment uart_tx_clocks is not handled $end
$comment uart_tx_fpga_out is not handled $end
$comment uart_tx_data_in is not handled $end
$comment uart_tx_data_out is not handled $end
$var reg 10 & transmit_register[9:0] $end
$var integer 32 ' transmit_bit_counter $end
$var integer 32 ( transmit_data_bit_counter $end
$upscope $end
$upscope $end
$enddefinitions $end
#0
0!
1"
0#
0$
b0 %
b0000000000 &
b0 '
b0 (
#500000
#1000000
1!
1#
1$
b1 %
b101 '
#1500000
0#
#2000000
1#
b10 %
#2500000
0#
#3000000
1#
b11 %
#3500000
0#
#4000000
1#
b100 %
#4500000
0#
#5000000
1#
b101 %
#5500000
0#
#6000000
1#
b110 %
b0101011000 &
#6500000
0#
#7000000
1#
b111 %
b100 '
#7500000
0#
#8000000
1#
b1000 %
b11 '
#8500000
0#
#9000000
1#
b1001 %
b10 '
#9500000
0#
#10000000
1#
b1010 %
b1 '
#10500000
0#
#11000000
1#
b1011 %
b0 '
#11500000
0#
#12000000
1#
b1100 %
b1010110001 &
b101 '
b1 (
#12500000
0#
#13000000
1#
b1101 %
b100 '
#13500000
0#
#14000000
1#
b1110 %
b11 '
#14500000
0#
#15000000
1#
b1111 %
b10 '
#15500000
0#
#16000000
1#
b10000 %
b1 '
#16500000
0#
#17000000
1#
b10001 %
b0 '
#17500000
0#
#18000000
1#
b10010 %
b0101100011 &
b101 '
b10 (
#18500000
0#
#19000000
1#
b10011 %
b100 '
#19500000
0#
#20000000
1#
b10100 %
b11 '
#20500000
0#
#21000000
1#
b10101 %
b10 '
#21500000
0#
#22000000
1#
b10110 %
b1 '
#22500000
0#
#23000000
1#
b10111 %
b0 '
#23500000
0#
#24000000
1#
b11000 %
b1011000111 &
b101 '
b11 (
#24500000
0#
#25000000
1#
b11001 %
b100 '
#25500000
0#
#26000000
1#
b11010 %
b11 '
#26500000
0#
#27000000
1#
b11011 %
b10 '
#27500000
0#
#28000000
1#
b11100 %
b1 '
#28500000
0#
#29000000
1#
b11101 %
b0 '
#29500000
0#
#30000000
1#
b11110 %
b0110001111 &
b101 '
b100 (
#30500000
0#
#31000000
1#
b11111 %
b100 '
#31500000
0#
#32000000
1#
b100000 %
b11 '
#32500000
0#
#33000000
1#
b100001 %
b10 '
#33500000
0#
#34000000
1#
b100010 %
b1 '
#34500000
0#
#35000000
1#
b100011 %
b0 '
#35500000
0#
#36000000
1#
b100100 %
b1100011111 &
b101 '
b101 (
#36500000
0#
#37000000
1#
b100101 %
b100 '
#37500000
0#
#38000000
1#
b100110 %
b11 '
#38500000
0#
#39000000
1#
b100111 %
b10 '
#39500000
0#
#40000000
1#
b101000 %
b1 '
#40500000
0#
#41000000
1#
b101001 %
b0 '
#41500000
0#
#42000000
1#
b101010 %
b1000111111 &
b101 '
b110 (
#42500000
0#
#43000000
1#
b101011 %
b100 '
#43500000
0#
#44000000
1#
b101100 %
b11 '
#44500000
0#
#45000000
1#
b101101 %
b10 '
#45500000
0#
#46000000
1#
b101110 %
b1 '
#46500000
0#
#47000000
1#
b101111 %
b0 '
#47500000
0#
#48000000
1#
b110000 %
b0001111111 &
b101 '
b111 (
#48500000
0#
#49000000
1#
b110001 %
b100 '
#49500000
0#
#50000000
1#
b110010 %
b11 '
#50500000
0#
#51000000
1#
b110011 %
b10 '
#51500000
0#
#52000000
1#
b110100 %
b1 '
#52500000
0#
#53000000
1#
b110101 %
b0 '
#53500000
0#
#54000000
1#
b110110 %
b0011111111 &
b101 '
b1000 (
#54500000
0#
#55000000
1#
b110111 %
b100 '
#55500000
0#
#56000000
1#
b111000 %
b11 '
#56500000
0#
#57000000
1#
b111001 %
b10 '
#57500000
0#
#58000000
1#
b111010 %
b1 '
#58500000
0#
#59000000
1#
b111011 %
b0 '
#59500000
0#
#60000000
1#
b111100 %
b0111111111 &
b101 '
b1001 (
#60500000
0#
#61000000
1#
b111101 %
b100 '
#61500000
0#
#62000000
1#
b111110 %
b11 '
#62500000
0#
#63000000
1#
b111111 %
b10 '
#63500000
0#
#64000000
1#
b1000000 %
b1 '
#64500000
0#
#65000000
1#
b1000001 %
b0 '
#65500000
0#
#66000000
1#
b1000010 %
b1111111111 &
b101 '
b1010 (
#66500000
0#
#67000000
1#
b1000011 %
b0 (
#67500000
0#
#68000000
1#
b1000100 %
#68500000
0#
#69000000
1#
b1000101 %
#69500000
0#
#70000000
1#
b1000110 %
#70500000
0#
#71000000
1#
b1000111 %
#71500000
0#
#72000000
1#
b1001000 %
#72500000
0#
#73000000
1#
b1001001 %
#73500000
0#
#74000000
1#
b1001010 %
#74500000
0#
#75000000
1#
b1001011 %
#75500000
0#
#76000000
1#
b1001100 %
#76500000
0#
#77000000
1#
b1001101 %
#77500000
0#
#78000000
1#
b1001110 %
#78500000
0#
#79000000
1#
b1001111 %
#79500000
0#
#80000000
1#
b1010000 %
#80500000
0#
#81000000
1#
b1010001 %
#81500000
0#
#82000000
1#
b1010010 %
#82500000
0#
#83000000
1#
b1010011 %
#83500000
0#
#84000000
1#
b1010100 %
#84500000
0#
#85000000
1#
b1010101 %
#85500000
0#
#86000000
1#
b1010110 %
#86500000
0#
#87000000
1#
b1010111 %
#87500000
0#
#88000000
1#
b1011000 %
#88500000
0#
#89000000
1#
b1011001 %
#89500000
0#
#90000000
1#
b1011010 %
#90500000
0#
#91000000
1#
b1011011 %
#91500000
0#
#92000000
1#
b1011100 %
#92500000
0#
#93000000
1#
b1011101 %
#93500000
0#
#94000000
1#
b1011110 %
#94500000
0#
#95000000
1#
b1011111 %
#95500000
0#
#96000000
1#
b1100000 %
#96500000
0#
#97000000
1#
b1100001 %
#97500000
0#
#98000000
1#
b1100010 %
#98500000
0#
#99000000
1#
b1100011 %
#99500000
0#
#100000000
1#
b1100100 %
#100500000
0#
#101000000
1#
b1100101 %
#101500000
0#
#102000000
1#
b1100110 %
#102500000
0#
#103000000
1#
b1100111 %
#103500000
0#
#104000000
1#
b1101000 %
#104500000
0#
#105000000
1#
b1101001 %
#105500000
0#
#106000000
1#
b1101010 %
#106500000
0#
#107000000
1#
b1101011 %
#107500000
0#
#108000000
1#
b1101100 %
#108500000
0#
#109000000
1#
b1101101 %
#109500000
0#
#110000000
1#
b1101110 %
#110500000
0#
#111000000
1#
b1101111 %
#111500000
0#
#112000000
1#
b1110000 %
#112500000
0#
#113000000
1#
b1110001 %
#113500000
0#
#114000000
1#
b1110010 %
#114500000
0#
#115000000
1#
b1110011 %
#115500000
0#
#116000000
1#
b1110100 %
#116500000
0#
#117000000
1#
b1110101 %
#117500000
0#
#118000000
1#
b1110110 %
#118500000
0#
#119000000
1#
b1110111 %
#119500000
0#
#120000000
1#
b1111000 %
#120500000
0#
#121000000
1#
b1111001 %
#121500000
0#
#122000000
1#
b1111010 %
#122500000
0#
#123000000
1#
b1111011 %
#123500000
0#
#124000000
1#
b1111100 %
#124500000
0#
#125000000
1#
b1111101 %
#125500000
0#
#126000000
1#
b1111110 %
#126500000
0#
#127000000
1#
b1111111 %
#127500000
0#
#128000000
1#
b10000000 %
#128500000
0#
#129000000
1#
b10000001 %
#129500000
0#
#130000000
1#
b10000010 %
#130500000
0#
#131000000
1#
b10000011 %
#131500000
0#
#132000000
1#
b10000100 %
#132500000
0#
#133000000
1#
b10000101 %
#133500000
0#
#134000000
1#
b10000110 %
#134500000
0#
#135000000
1#
b10000111 %
#135500000
0#
#136000000
1#
b10001000 %
#136500000
0#
#137000000
1#
b10001001 %
#137500000
0#
#138000000
1#
b10001010 %
#138500000
0#
#139000000
1#
b10001011 %
#139500000
0#
#140000000
1#
b10001100 %
#140500000
0#
#141000000
1#
b10001101 %
#141500000
0#
#142000000
1#
b10001110 %
#142500000
0#
#143000000
1#
b10001111 %
#143500000
0#
#144000000
1#
b10010000 %
#144500000
0#
#145000000
1#
b10010001 %
#145500000
0#
#146000000
1#
b10010010 %
#146500000
0#
#147000000
1#
b10010011 %
#147500000
0#
#148000000
1#
b10010100 %
#148500000
0#
#149000000
1#
b10010101 %
#149500000
0#
#150000000
0"
1#
b10010110 %
